single_cycle_edition/src/memory.sv
// memory.sv

module memory #(
    parameter WORDS = 64
) (
    input logic clk,
    input logic [31:0] address,
    input logic [31:0] write_data,
    input logic write_enable,
    input logic rst_n,

    output logic [31:0] read_data
);

/*
* This memory is byte addressed
* But have no support for mis-aligned write nor reads.
*/

reg [31:0] mem [0:WORDS-1];  // Memory array of words (32-bits)

always @(posedge clk) begin
    // reset logic
    if (rst_n == 1'b0) begin
        for (int i = 0; i < WORDS; i++) begin
            mem[i] <= 32'b0;  
        end
    end
    else if (write_enable) begin
        // Ensure the address is aligned to a word boundary
        // If not, we ignore the write
        if (address[1:0] == 2'b00) begin 
            //here, address[31:2] is the word index
            mem[address[7:2]] <= write_data;
        end
    end
end

// Read logic
always_comb begin
    //here, address[31:2] is the word index
    read_data = mem[address[7:2]]; 
end

endmodule

single_cycle_edition/tb/memory/dump.vcd
$version Generated by VerilatedVcd $end
$timescale 1ps $end
 $scope module $rootio $end
  $var wire 1 " clk $end
  $var wire 32 # address [31:0] $end
  $var wire 32 $ write_data [31:0] $end
  $var wire 1 % write_enable $end
  $var wire 1 & rst_n $end
  $var wire 32 ' read_data [31:0] $end
 $upscope $end
 $scope module memory $end
  $var wire 32 . WORDS [31:0] $end
  $var wire 1 ( clk $end
  $var wire 32 ) address [31:0] $end
  $var wire 32 * write_data [31:0] $end
  $var wire 1 + write_enable $end
  $var wire 1 , rst_n $end
  $var wire 32 - read_data [31:0] $end
 $upscope $end
$enddefinitions $end


#0
1"
b00000000000000000000000000000000 #
b00000000000000000000000000000000 $
0%
0&
b00000000000000000000000000000000 '
1(
b00000000000000000000000000000000 )
b00000000000000000000000000000000 *
0+
0,
b00000000000000000000000000000000 -
b00000000000000000000000001000000 .
#500
0"
0(
#1000
1"
1&
1(
1,
#1500
0"
0(
#2000
1"
1(
#2500
0"
0(
#3000
1"
b00000000000000000000000000000001 #
1(
b00000000000000000000000000000001 )
#3500
0"
0(
#4000
1"
b00000000000000000000000000000010 #
1(
b00000000000000000000000000000010 )
#4500
0"
0(
#5000
1"
b00000000000000000000000000000011 #
1(
b00000000000000000000000000000011 )
#5500
0"
0(
#6000
1"
b00000000000000000000000000000100 #
1(
b00000000000000000000000000000100 )
#6500
0"
0(
#7000
1"
b00000000000000000000000000000101 #
1(
b00000000000000000000000000000101 )
#7500
0"
0(
#8000
1"
b00000000000000000000000000000110 #
1(
b00000000000000000000000000000110 )
#8500
0"
0(
#9000
1"
b00000000000000000000000000000111 #
1(
b00000000000000000000000000000111 )
#9500
0"
0(
#10000
1"
b00000000000000000000000000001000 #
1(
b00000000000000000000000000001000 )
#10500
0"
0(
#11000
1"
b00000000000000000000000000001001 #
1(
b00000000000000000000000000001001 )
#11500
0"
0(
#12000
1"
b00000000000000000000000000001010 #
1(
b00000000000000000000000000001010 )
#12500
0"
0(
#13000
1"
b00000000000000000000000000001011 #
1(
b00000000000000000000000000001011 )
#13500
0"
0(
#14000
1"
b00000000000000000000000000001100 #
1(
b00000000000000000000000000001100 )
#14500
0"
0(
#15000
1"
b00000000000000000000000000001101 #
1(
b00000000000000000000000000001101 )
#15500
0"
0(
#16000
1"
b00000000000000000000000000001110 #
1(
b00000000000000000000000000001110 )
#16500
0"
0(
#17000
1"
b00000000000000000000000000001111 #
1(
b00000000000000000000000000001111 )
#17500
0"
0(
#18000
1"
b00000000000000000000000000010000 #
1(
b00000000000000000000000000010000 )
#18500
0"
0(
#19000
1"
b00000000000000000000000000010001 #
1(
b00000000000000000000000000010001 )
#19500
0"
0(
#20000
1"
b00000000000000000000000000010010 #
1(
b00000000000000000000000000010010 )
#20500
0"
0(
#21000
1"
b00000000000000000000000000010011 #
1(
b00000000000000000000000000010011 )
#21500
0"
0(
#22000
1"
b00000000000000000000000000010100 #
1(
b00000000000000000000000000010100 )
#22500
0"
0(
#23000
1"
b00000000000000000000000000010101 #
1(
b00000000000000000000000000010101 )
#23500
0"
0(
#24000
1"
b00000000000000000000000000010110 #
1(
b00000000000000000000000000010110 )
#24500
0"
0(
#25000
1"
b00000000000000000000000000010111 #
1(
b00000000000000000000000000010111 )
#25500
0"
0(
#26000
1"
b00000000000000000000000000011000 #
1(
b00000000000000000000000000011000 )
#26500
0"
0(
#27000
1"
b00000000000000000000000000011001 #
1(
b00000000000000000000000000011001 )
#27500
0"
0(
#28000
1"
b00000000000000000000000000011010 #
1(
b00000000000000000000000000011010 )
#28500
0"
0(
#29000
1"
b00000000000000000000000000011011 #
1(
b00000000000000000000000000011011 )
#29500
0"
0(
#30000
1"
b00000000000000000000000000011100 #
1(
b00000000000000000000000000011100 )
#30500
0"
0(
#31000
1"
b00000000000000000000000000011101 #
1(
b00000000000000000000000000011101 )
#31500
0"
0(
#32000
1"
b00000000000000000000000000011110 #
1(
b00000000000000000000000000011110 )
#32500
0"
0(
#33000
1"
b00000000000000000000000000011111 #
1(
b00000000000000000000000000011111 )
#33500
0"
0(
#34000
1"
b00000000000000000000000000100000 #
1(
b00000000000000000000000000100000 )
#34500
0"
0(
#35000
1"
b00000000000000000000000000100001 #
1(
b00000000000000000000000000100001 )
#35500
0"
0(
#36000
1"
b00000000000000000000000000100010 #
1(
b00000000000000000000000000100010 )
#36500
0"
0(
#37000
1"
b00000000000000000000000000100011 #
1(
b00000000000000000000000000100011 )
#37500
0"
0(
#38000
1"
b00000000000000000000000000100100 #
1(
b00000000000000000000000000100100 )
#38500
0"
0(
#39000
1"
b00000000000000000000000000100101 #
1(
b00000000000000000000000000100101 )
#39500
0"
0(
#40000
1"
b00000000000000000000000000100110 #
1(
b00000000000000000000000000100110 )
#40500
0"
0(
#41000
1"
b00000000000000000000000000100111 #
1(
b00000000000000000000000000100111 )
#41500
0"
0(
#42000
1"
b00000000000000000000000000101000 #
1(
b00000000000000000000000000101000 )
#42500
0"
0(
#43000
1"
b00000000000000000000000000101001 #
1(
b00000000000000000000000000101001 )
#43500
0"
0(
#44000
1"
b00000000000000000000000000101010 #
1(
b00000000000000000000000000101010 )
#44500
0"
0(
#45000
1"
b00000000000000000000000000101011 #
1(
b00000000000000000000000000101011 )
#45500
0"
0(
#46000
1"
b00000000000000000000000000101100 #
1(
b00000000000000000000000000101100 )
#46500
0"
0(
#47000
1"
b00000000000000000000000000101101 #
1(
b00000000000000000000000000101101 )
#47500
0"
0(
#48000
1"
b00000000000000000000000000101110 #
1(
b00000000000000000000000000101110 )
#48500
0"
0(
#49000
1"
b00000000000000000000000000101111 #
1(
b00000000000000000000000000101111 )
#49500
0"
0(
#50000
1"
b00000000000000000000000000110000 #
1(
b00000000000000000000000000110000 )
#50500
0"
0(
#51000
1"
b00000000000000000000000000110001 #
1(
b00000000000000000000000000110001 )
#51500
0"
0(
#52000
1"
b00000000000000000000000000110010 #
1(
b00000000000000000000000000110010 )
#52500
0"
0(
#53000
1"
b00000000000000000000000000110011 #
1(
b00000000000000000000000000110011 )
#53500
0"
0(
#54000
1"
b00000000000000000000000000110100 #
1(
b00000000000000000000000000110100 )
#54500
0"
0(
#55000
1"
b00000000000000000000000000110101 #
1(
b00000000000000000000000000110101 )
#55500
0"
0(
#56000
1"
b00000000000000000000000000110110 #
1(
b00000000000000000000000000110110 )
#56500
0"
0(
#57000
1"
b00000000000000000000000000110111 #
1(
b00000000000000000000000000110111 )
#57500
0"
0(
#58000
1"
b00000000000000000000000000111000 #
1(
b00000000000000000000000000111000 )
#58500
0"
0(
#59000
1"
b00000000000000000000000000111001 #
1(
b00000000000000000000000000111001 )
#59500
0"
0(
#60000
1"
b00000000000000000000000000111010 #
1(
b00000000000000000000000000111010 )
#60500
0"
0(
#61000
1"
b00000000000000000000000000111011 #
1(
b00000000000000000000000000111011 )
#61500
0"
0(
#62000
1"
b00000000000000000000000000111100 #
1(
b00000000000000000000000000111100 )
#62500
0"
0(
#63000
1"
b00000000000000000000000000111101 #
1(
b00000000000000000000000000111101 )
#63500
0"
0(
#64000
1"
b00000000000000000000000000111110 #
1(
b00000000000000000000000000111110 )
#64500
0"
0(
#65000
1"
b00000000000000000000000000111111 #
1(
b00000000000000000000000000111111 )
#65500
0"
0(
#66000
1"
b00000000000000000000000000000000 #
b11011110101011011011111011101111 $
b11011110101011011011111011101111 '
1(
b00000000000000000000000000000000 )
b11011110101011011011111011101111 *
b11011110101011011011111011101111 -
#66500
0"
0(
#67000
1"
1(
#67500
0"
0(
#68000
1"
b00000000000000000000000000000100 #
b11001010111111101011101010111110 $
1%
b00000000000000000000000000000000 '
1(
b00000000000000000000000000000100 )
b11001010111111101011101010111110 *
1+
b00000000000000000000000000000000 -
#68500
0"
0(
#69000
1"
0%
b11001010111111101011101010111110 '
1(
0+
b11001010111111101011101010111110 -
#69500
0"
0(
#70000
1"
1(
#70500
0"
0(
#71000
1"
b00000000000000000000000000001000 #
b00010010001101000101011001111000 $
1%
b00000000000000000000000000000000 '
1(
b00000000000000000000000000001000 )
b00010010001101000101011001111000 *
1+
b00000000000000000000000000000000 -
#71500
0"
0(
#72000
1"
0%
b00010010001101000101011001111000 '
1(
0+
b00010010001101000101011001111000 -
#72500
0"
0(
#73000
1"
1(
#73500
0"
0(
#74000
1"
b00000000000000000000000000001100 #
b10100101101001011010010110100101 $
1%
b00000000000000000000000000000000 '
1(
b00000000000000000000000000001100 )
b10100101101001011010010110100101 *
1+
b00000000000000000000000000000000 -
#74500
0"
0(
#75000
1"
0%
b10100101101001011010010110100101 '
1(
0+
b10100101101001011010010110100101 -
